<?xml version="1.0" encoding="utf-8"?>
<phrases>
  <phrase title="admin_navigation.xftt_hitnrun_list" version_id="1000037" version_string="1.0.0 Beta 7"><![CDATA[Hit & Run Members List]]></phrase>
  <phrase title="admin_navigation.xftt_hitnrun_settings" version_id="1000032" version_string="1.0.0 Beta 2"><![CDATA[Hit & Run Settings]]></phrase>
  <phrase title="cron_entry.xfdev_check_hitnrun" version_id="1000010" version_string="1.0.0 Alpha"><![CDATA[HitnRun - Check Hit and Run]]></phrase>
  <phrase title="cron_entry.xfdev_disable_access_hnr" version_id="1000013" version_string="1.0.0 Alpha 3"><![CDATA[Disable/Enable Torrent Download Access]]></phrase>
  <phrase title="cron_entry.xfdev_recheck_hit_torrent" version_id="1000010" version_string="1.0.0 Alpha"><![CDATA[HitnRun - Re-Check Hit Torrents]]></phrase>
  <phrase title="cron_entry.xfdev_recheck_zap_hitnrun" version_id="1000010" version_string="1.0.0 Alpha"><![CDATA[HitnRun - Re-Check Zapped Torrents]]></phrase>
  <phrase title="dbtech_shop_itemtype_description.awards" version_id="1000031" version_string="1.0.0 Beta 1"><![CDATA[Purchase an Award]]></phrase>
  <phrase title="download_will_disable_after_x_hnrs_for_x_tolerance_period" version_id="1000033" version_string="1.0.0 Beta 3"><![CDATA[Your Torrent Download Access will be disabled if you have <b>{disable_leech_hnrs} Hit & Runs</b> for <b>{disable_leech_hnrs_tolerance}</b>]]></phrase>
  <phrase title="hit_and_run" version_id="1000031" version_string="1.0.0 Beta 1"><![CDATA[Hit & Run]]></phrase>
  <phrase title="hitnrun_has_been_successfully_removed" version_id="1000032" version_string="1.0.0 Beta 2"><![CDATA[Hit and Run has been Successfully Removed]]></phrase>
  <phrase title="hitnrun_members_list" version_id="1000037" version_string="1.0.0 Beta 7"><![CDATA[Hit & Run Members List]]></phrase>
  <phrase title="hitnrun_of_x" version_id="1000031" version_string="1.0.0 Beta 1"><![CDATA[Hit & Runs of {name}]]></phrase>
  <phrase title="hnr_will_be_checked_after_trigger_bytes" version_id="1000033" version_string="1.0.0 Beta 3"><![CDATA[Hit & Run will only be checked when you download torrents larger than <b>{down_trigger_bytes}</b>]]></phrase>
  <phrase title="hnr_will_be_checked_after_x_tolerance_period" version_id="1000033" version_string="1.0.0 Beta 3"><![CDATA[Hit & Run will check only if your torrent is inactive for <b>{tolerance_period}</b> and you will get Hit & Run if you don't meet the Hit & Run Rules mentioned above.]]></phrase>
  <phrase title="nav.xfdev_hitnrun_myhnr" version_id="1000010" version_string="1.0.0 Alpha"><![CDATA[My Hit & Run]]></phrase>
  <phrase title="option.xfdevHitnRunBypassUsergroups" version_id="1000033" version_string="1.0.0 Beta 3"><![CDATA[Bypass Hit & Run Check for Selected Usergroups]]></phrase>
  <phrase title="option.xfdev_hintrun_check_method" version_id="1000010" version_string="1.0.0 Alpha"><![CDATA[Hit & Run Check Method]]></phrase>
  <phrase title="option.xfdev_hitnrun_1mbtobonus" version_id="1000010" version_string="1.0.0 Alpha"><![CDATA[Define 1 MB in Bonus Points]]></phrase>
  <phrase title="option.xfdev_hitnrun_block_leech" version_id="1000010" version_string="1.0.0 Alpha"><![CDATA[Block Leech]]></phrase>
  <phrase title="option.xfdev_hitnrun_check_tolerance_period" version_id="1000010" version_string="1.0.0 Alpha"><![CDATA[Tolerance Period (in Hours)]]></phrase>
  <phrase title="option.xfdev_hitnrun_download_trigger" version_id="1000010" version_string="1.0.0 Alpha"><![CDATA[Download Trigger Bytes (in MBs)]]></phrase>
  <phrase title="option.xfdev_hitnrun_enable" version_id="1000010" version_string="1.0.0 Alpha"><![CDATA[Enable Hit and Run]]></phrase>
  <phrase title="option.xfdev_hitnrun_minimum_ratio" version_id="1000010" version_string="1.0.0 Alpha"><![CDATA[Minimum Ratio]]></phrase>
  <phrase title="option.xfdev_hitnrun_minimum_seed_hours" version_id="1000010" version_string="1.0.0 Alpha"><![CDATA[Minimum Seeding Time (in Hours)]]></phrase>
  <phrase title="option.xfdev_hitnrun_send_conversation_on_block_leech" version_id="1000032" version_string="1.0.0 Beta 2"><![CDATA[Send Conversation on Leech Block]]></phrase>
  <phrase title="option.xfdev_hitnrun_zap_multiplier" version_id="1000037" version_string="1.0.0 Beta 7"><![CDATA[Zap Upload Multiplier]]></phrase>
  <phrase title="option_explain.xfdevHitnRunBypassUsergroups" version_id="1000033" version_string="1.0.0 Beta 3"><![CDATA[This option allows you to bypass hit and run checks for selected usergroups.]]></phrase>
  <phrase title="option_explain.xfdev_hintrun_check_method" version_id="1000010" version_string="1.0.0 Alpha"><![CDATA[Select the Hit and Run Check Method to Implement]]></phrase>
  <phrase title="option_explain.xfdev_hitnrun_1mbtobonus" version_id="1000010" version_string="1.0.0 Alpha"><![CDATA[Define the value of seedbonus for 1 MB, accordingly user will be charged seedbonus while zapping hnr using seedbonus.]]></phrase>
  <phrase title="option_explain.xfdev_hitnrun_block_leech" version_id="1000010" version_string="1.0.0 Alpha"><![CDATA[Disable Download For Users after they Get a No. of Hit & Run]]></phrase>
  <phrase title="option_explain.xfdev_hitnrun_check_tolerance_period" version_id="1000010" version_string="1.0.0 Alpha"><![CDATA[Hit and Run will be checked once the last announce period is higher than Tolerance Period]]></phrase>
  <phrase title="option_explain.xfdev_hitnrun_download_trigger" version_id="1000010" version_string="1.0.0 Alpha"><![CDATA[Enter the amount after downloading greater than that amount Hit and Run will be checked for a user]]></phrase>
  <phrase title="option_explain.xfdev_hitnrun_enable" version_id="1000010" version_string="1.0.0 Alpha"><![CDATA[Enable Hit and Run System Throughout the Forum]]></phrase>
  <phrase title="option_explain.xfdev_hitnrun_minimum_ratio" version_id="1000010" version_string="1.0.0 Alpha"><![CDATA[Enter Minimum Ratio which users must satisfy to avoid Hit and Run]]></phrase>
  <phrase title="option_explain.xfdev_hitnrun_minimum_seed_hours" version_id="1000010" version_string="1.0.0 Alpha"><![CDATA[Enter the Minimum Seeding Time which should be completed by user to avoid Hit & Run (168 Hours = 7 Days)]]></phrase>
  <phrase title="option_explain.xfdev_hitnrun_send_conversation_on_block_leech" version_id="1000032" version_string="1.0.0 Beta 2"><![CDATA[It sends a conversation to the user, if his Download Access is Disabled due to Hit and Run]]></phrase>
  <phrase title="option_explain.xfdev_hitnrun_zap_multiplier" version_id="1000037" version_string="1.0.0 Beta 7"><![CDATA[It will multiply the upload amount of zapping. E.g :- X Torrent needs 5 GB to zap h&r, and if zap multiplier is set to 2, user will have to use 10GB to zap that torrent]]></phrase>
  <phrase title="option_group.xfdev_hitnrun_settings" version_id="1000010" version_string="1.0.0 Alpha"><![CDATA[Hit & Run Settings]]></phrase>
  <phrase title="option_group_description.xfdev_hitnrun_settings" version_id="1000010" version_string="1.0.0 Alpha"><![CDATA[Setup Hit and Run Settings]]></phrase>
  <phrase title="permission.xfdevHitandRunModerator_canDeleteOthersHnr" version_id="1000031" version_string="1.0.0 Beta 1"><![CDATA[Delete Others H&R]]></phrase>
  <phrase title="permission.xfdevHitandRunModerator_canSeeOthersHnr" version_id="1000031" version_string="1.0.0 Beta 1"><![CDATA[View Others H&R]]></phrase>
  <phrase title="permission_interface.xfdevHitandRunModeratorPermissions" version_id="1000031" version_string="1.0.0 Beta 1"><![CDATA[XFDev - Hit & Run Moderator Permissions]]></phrase>
  <phrase title="ratio_only" version_id="1000033" version_string="1.0.0 Beta 3"><![CDATA[Ratio Only]]></phrase>
  <phrase title="remove_hnr" version_id="1000032" version_string="1.0.0 Beta 2"><![CDATA[Remove H&R]]></phrase>
  <phrase title="remove_users_hitnrun" version_id="1000032" version_string="1.0.0 Beta 2"><![CDATA[Remove Users Hit and Run]]></phrase>
  <phrase title="remove_users_hitnrun_ques" version_id="1000032" version_string="1.0.0 Beta 2"><![CDATA[Are you sure you want to remove this hit and run?]]></phrase>
  <phrase title="reset_users_hnr" version_id="1000012" version_string="1.0.0 Alpha 2"><![CDATA[Reset Users Hit & Runs]]></phrase>
  <phrase title="reset_users_hnr_explain" version_id="1000012" version_string="1.0.0 Alpha 2"><![CDATA[It will remove all the hit and runs of upgraded users and make all their current torrents skip hit and run check.]]></phrase>
  <phrase title="seed_and_ratio" version_id="1000033" version_string="1.0.0 Beta 3"><![CDATA[Seedtime and Ratio]]></phrase>
  <phrase title="seed_only" version_id="1000033" version_string="1.0.0 Beta 3"><![CDATA[Seedtime Only]]></phrase>
  <phrase title="seed_or_ratio" version_id="1000033" version_string="1.0.0 Beta 3"><![CDATA[Seedtime or Ratio]]></phrase>
  <phrase title="seedtime" version_id="1000031" version_string="1.0.0 Beta 1"><![CDATA[Seedtime]]></phrase>
  <phrase title="this_peer_doesnt_exist_or_doesnt_belongs_to_this_user" version_id="1000032" version_string="1.0.0 Beta 2"><![CDATA[This peer doesn't exist or doesn't belong to this user.]]></phrase>
  <phrase title="this_peer_doesnt_exist_or_doesnt_belongs_to_you" version_id="1000031" version_string="1.0.0 Beta 1"><![CDATA[This Peer Doesn't Exist or Doesn't Belongs to You]]></phrase>
  <phrase title="user_dont_have_any_hnrs" version_id="1000032" version_string="1.0.0 Beta 2"><![CDATA[User don't have hit and runs.]]></phrase>
  <phrase title="xfdev_currently_enabled_hnr" version_id="1000033" version_string="1.0.0 Beta 3"><![CDATA[Currently <b>{hnr_method}</b> based Hit & Run is enabled]]></phrase>
  <phrase title="xfdev_hnr_rules" version_id="1000033" version_string="1.0.0 Beta 3"><![CDATA[Hit & Run Rules]]></phrase>
  <phrase title="xfdev_xftt_hitnrun_downloaded" version_id="1000037" version_string="1.0.0 Beta 7"><![CDATA[Downloaded]]></phrase>
  <phrase title="xfdev_xftt_hitnrun_last_checked" version_id="1000037" version_string="1.0.0 Beta 7"><![CDATA[H&R Last Checked]]></phrase>
  <phrase title="xfdev_xftt_hitnrun_left" version_id="1000037" version_string="1.0.0 Beta 7"><![CDATA[Left Amount]]></phrase>
  <phrase title="xfdev_xftt_hitnrun_torrent" version_id="1000037" version_string="1.0.0 Beta 7"><![CDATA[Torrent]]></phrase>
  <phrase title="xfdev_xftt_hitnrun_uploaded" version_id="1000037" version_string="1.0.0 Beta 7"><![CDATA[Uploaded]]></phrase>
  <phrase title="xfdev_xftt_hitnrun_user" version_id="1000037" version_string="1.0.0 Beta 7"><![CDATA[User]]></phrase>
  <phrase title="you_dont_have_any_hnrs" version_id="1000032" version_string="1.0.0 Beta 2"><![CDATA[You don't have any hit and runs.]]></phrase>
  <phrase title="you_dont_have_enough_seedbonus" version_id="1000031" version_string="1.0.0 Beta 1"><![CDATA[You don't have enough seedbonus]]></phrase>
  <phrase title="you_dont_have_enough_upload_data" version_id="1000031" version_string="1.0.0 Beta 1"><![CDATA[You don't have enough Upload Data]]></phrase>
  <phrase title="you_must_seed_for_x_hours" version_id="1000033" version_string="1.0.0 Beta 3"><![CDATA[You must seed Torrents for <b>{min_seed_hours}</b>]]></phrase>
  <phrase title="you_must_seed_for_x_hours_and_upload_for_x_ratio" version_id="1000033" version_string="1.0.0 Beta 3"><![CDATA[You must seed Torrents for <b>{min_seed_hours}</b> and  Upload torrent for <b>1:{min_ratio} Ratio</b>]]></phrase>
  <phrase title="you_must_seed_for_x_hours_or_upload_for_x_ratio" version_id="1000033" version_string="1.0.0 Beta 3"><![CDATA[You must seed Torrents for <b>{min_seed_hours}</b> or  Upload torrent for <b>1:{min_ratio} Ratio</b>]]></phrase>
  <phrase title="you_must_upload_for_x_ratio" version_id="1000033" version_string="1.0.0 Beta 3"><![CDATA[You must upload torrent for <b>1:{min_ratio} Ratio</b>]]></phrase>
  <phrase title="your_download_access_disabled_due_to_hnr" version_id="1000032" version_string="1.0.0 Beta 2"><![CDATA[Your Download Access has been disabled due to Hit & Runs]]></phrase>
  <phrase title="your_hnr" version_id="1000010" version_string="1.0.0 Alpha"><![CDATA[Your Hit & Runs]]></phrase>
  <phrase title="zap" version_id="1000012" version_string="1.0.0 Alpha 2"><![CDATA[Zap]]></phrase>
</phrases>
